{
  "Elasticity": {
    "objective": "MinimizeCompliance",
    "domain_parameters": {
      "width": 10.0,
      "height": 5.0,
      "fem_step_size": 0.03,
      "dem_step_size": 3.0,
      "penalties": [
        3.0
      ],
      "volume_fraction": 0.4
    },
    "problem_parameters": {
      "fixed_sides": [
        "Left"
      ],
      "body_force": null,
      "tractions": [
        {
          "side": "Right",
          "center": 2.5,
          "length": 0.1111111111111111,
          "value": [
            0.0,
            -2000.0
          ]
        }
      ],
      "young_modulus": 200000.0,
      "poisson_ratio": 0.3
    }
  }
}